gitlab_auto_release
