Metadata-Version: 2.1
Name: gitlab-auto-release
Version: 2.0.4
Summary: Python script which is used to create releases on GitLab
Home-page: https://gitlab.com/gitlab-automation-toolkit/gitlab-auto-release
Author: Haseeb Majid
Author-email: me@haseebmajid.dev
License: Apache License
Platform: UNKNOWN
Classifier: Programming Language :: Python
Classifier: Intended Audience :: Developers
Classifier: Operating System :: OS Independent
Classifier: Topic :: Software Development :: Libraries :: Python Modules
Requires-Python: ~=3.7
